{"total_cases":{"counties":["Shelby","Williamson","Davidson","Hamilton","Knox","Sullivan","Campbell","Jefferson","Rutherford","Anderson","Bradley","Sevier","Sumner","Tipton","Cheatham","Dekalb","McMinn","Maury","Wilson","Chester","Cumberland","Fayette","Hardin","Loudon","Marion","Montgomery","Putnam","Robertson","Blount","Carroll","Cocke","Dickson","Dyer","Franklin","Greene","Hamblen","Monroe","Roane","Scott","Washington","Humphreys","Gibson","Grundy","Henry","Hickman","Houston","Lawrence","Lewis","Lincoln","Macon","Madison","Marshall","Overton","Perry","Polk","Claiborne","Hawkins","McNairy","Morgan","Meigs","Wayne","Henderson","Bedford","Bledsoe","Cannon","Coffee","Hardeman","Trousdale","Unicoi","Weakley","White","Benton","Haywood","Warren","Carter","Decatur","Grainger","Johnson","Smith","Obion","Union","Clay","Fentress","Giles","Lauderdale","Jackson","Sequatchie","Crockett","Hancock","Lake","Moore","Pickett","Rhea","Stewart","Van Buren"],"z":[7290,742,7253,1956,594,71,26,51,1888,69,305,342,1130,541,161,41,171,198,565,14,138,189,46,221,49,356,630,670,118,36,27,140,122,64,56,91,97,32,15,99,18,70,37,35,62,10,76,5,48,216,188,45,38,28,32,16,37,35,22,30,64,19,404,614,34,97,226,1464,52,36,51,8,39,36,23,15,22,26,46,68,9,11,15,24,71,21,23,21,1,689,5,4,243,17,5],"type":"cmap","mtitle":"Total COVID-19 Cases","hovtext":"Total cases:","col1":"rgb(255, 255, 255)","col2":"rgb(164, 225, 252)","col3":"rgb(105, 201, 245)","col4":"rgb(3, 175, 255)","col5":"rgb(0, 56, 120)"},"total_deaths":{"counties":["Shelby","Williamson","Davidson","Hamilton","Knox","Sullivan","Campbell","Jefferson","Rutherford","Anderson","Bradley","Sevier","Sumner","Tipton","Cheatham","Dekalb","McMinn","Maury","Wilson","Chester","Cumberland","Fayette","Hardin","Loudon","Marion","Montgomery","Putnam","Robertson","Blount","Carroll","Cocke","Dickson","Dyer","Franklin","Greene","Hamblen","Monroe","Roane","Scott","Washington","Humphreys","Gibson","Grundy","Henry","Hickman","Houston","Lawrence","Lewis","Lincoln","Macon","Madison","Marshall","Overton","Perry","Polk","Claiborne","Hawkins","McNairy","Morgan","Meigs","Wayne","Henderson","Bedford","Bledsoe","Cannon","Coffee","Hardeman","Trousdale","Unicoi","Weakley","White","Benton","Haywood","Warren","Carter","Decatur","Grainger","Johnson","Smith","Obion","Union","Clay","Fentress","Giles","Lauderdale","Jackson","Sequatchie","Crockett","Hancock","Lake","Moore","Pickett","Rhea","Stewart","Van Buren"],"z":[158,12,93,22,5,2,1,0,32,2,2,3,49,4,0,0,15,2,14,0,3,2,5,1,2,5,6,9,3,1,0,0,0,2,2,4,4,0,0,0,1,1,1,0,0,0,2,0,0,3,2,1,0,0,0,0,2,0,1,0,0,0,4,1,0,0,0,5,0,0,2,1,2,0,1,0,0,0,1,1,0,0,0,0,1,0,0,3,0,0,0,0,0,0,0],"type":"cmap","mtitle":"Total COVID-19 Deaths","hovtext":"Total deaths:","col1":"rgb(255, 255, 255)","col2":"rgb(255, 179, 179)","col3":"rgb(240, 101, 101)","col4":"rgb(199, 28, 28)","col5":"rgb(148, 0, 0)"},"daily_cases":{"counties":["Shelby","Williamson","Davidson","Hamilton","Knox","Sullivan","Campbell","Jefferson","Rutherford","Anderson","Bradley","Sevier","Sumner","Tipton","Cheatham","Dekalb","McMinn","Maury","Wilson","Chester","Cumberland","Fayette","Hardin","Loudon","Marion","Montgomery","Putnam","Robertson","Blount","Carroll","Cocke","Dickson","Dyer","Franklin","Greene","Hamblen","Monroe","Roane","Scott","Washington","Humphreys","Gibson","Grundy","Henry","Hickman","Houston","Lawrence","Lewis","Lincoln","Macon","Madison","Marshall","Overton","Perry","Polk","Claiborne","Hawkins","McNairy","Morgan","Meigs","Wayne","Henderson","Bedford","Bledsoe","Cannon","Coffee","Hardeman","Trousdale","Unicoi","Weakley","White","Benton","Haywood","Warren","Carter","Decatur","Grainger","Johnson","Smith","Obion","Union","Clay","Fentress","Giles","Lauderdale","Jackson","Sequatchie","Crockett","Hancock","Lake","Moore","Pickett","Rhea","Stewart","Van Buren"],"z":[107,12,171,75,21,0,1,3,37,3,2,45,11,7,2,0,1,21,21,0,1,3,2,7,0,15,18,12,3,0,0,0,6,0,1,-1,4,0,1,6,0,1,0,0,0,0,4,0,0,7,0,1,0,0,0,1,0,2,1,1,0,0,1,0,0,0,0,4,0,1,1,0,0,1,1,1,0,1,3,1,0,0,0,1,0,1,0,2,0,0,0,0,0,1,0],"type":"cmap","mtitle":"Daily COVID-19 Cases: 06/18/2020","hovtext":"New cases:","col1":"rgb(255, 255, 255)","col2":"rgb(164, 225, 252)","col3":"rgb(105, 201, 245)","col4":"rgb(3, 175, 255)","col5":"rgb(0, 56, 120)"},"daily_deaths":{"counties":["Shelby","Williamson","Davidson","Hamilton","Knox","Sullivan","Campbell","Jefferson","Rutherford","Anderson","Bradley","Sevier","Sumner","Tipton","Cheatham","Dekalb","McMinn","Maury","Wilson","Chester","Cumberland","Fayette","Hardin","Loudon","Marion","Montgomery","Putnam","Robertson","Blount","Carroll","Cocke","Dickson","Dyer","Franklin","Greene","Hamblen","Monroe","Roane","Scott","Washington","Humphreys","Gibson","Grundy","Henry","Hickman","Houston","Lawrence","Lewis","Lincoln","Macon","Madison","Marshall","Overton","Perry","Polk","Claiborne","Hawkins","McNairy","Morgan","Meigs","Wayne","Henderson","Bedford","Bledsoe","Cannon","Coffee","Hardeman","Trousdale","Unicoi","Weakley","White","Benton","Haywood","Warren","Carter","Decatur","Grainger","Johnson","Smith","Obion","Union","Clay","Fentress","Giles","Lauderdale","Jackson","Sequatchie","Crockett","Hancock","Lake","Moore","Pickett","Rhea","Stewart","Van Buren"],"z":[4,0,2,1,0,0,0,0,1,0,0,0,1,0,0,0,0,1,0,0,0,0,0,0,0,0,0,0,0,0,0,0,0,0,0,0,0,0,0,0,0,0,0,0,0,0,0,0,0,0,0,0,0,0,0,0,0,0,0,0,0,0,0,0,0,0,0,1,0,0,0,0,0,0,0,0,0,0,0,0,0,0,0,0,0,0,0,0,0,0,0,0,0,0,0],"type":"cmap","mtitle":"Daily COVID-19 Deaths: 06/18/2020","hovtext":"New deaths:","col1":"rgb(255, 255, 255)","col2":"rgb(252, 165, 164)","col3":"rgb(240, 101, 101)","col4":"rgb(199, 28, 28)","col5":"rgb(148, 0, 0)"},"testing":{"counties":["Shelby","Williamson","Davidson","Hamilton","Knox","Sullivan","Campbell","Jefferson","Rutherford","Anderson","Bradley","Sevier","Sumner","Tipton","Cheatham","Dekalb","McMinn","Maury","Wilson","Chester","Cumberland","Fayette","Hardin","Loudon","Marion","Montgomery","Putnam","Robertson","Blount","Carroll","Cocke","Dickson","Dyer","Franklin","Greene","Hamblen","Monroe","Roane","Scott","Washington","Humphreys","Gibson","Grundy","Henry","Hickman","Houston","Lawrence","Lewis","Lincoln","Macon","Madison","Marshall","Overton","Perry","Polk","Claiborne","Hawkins","McNairy","Morgan","Meigs","Wayne","Henderson","Bedford","Bledsoe","Cannon","Coffee","Hardeman","Trousdale","Unicoi","Weakley","White","Benton","Haywood","Warren","Carter","Decatur","Grainger","Johnson","Smith","Obion","Union","Clay","Fentress","Giles","Lauderdale","Jackson","Sequatchie","Crockett","Hancock","Lake","Moore","Pickett","Rhea","Stewart","Van Buren"],"z":[107564,14129,58991,21831,27587,5911,2346,3303,18550,6546,4844,6782,12096,6699,2734,1666,3718,4340,9420,831,5944,4653,2319,3499,1321,11119,8188,5853,5380,1748,1639,3185,2344,2507,3196,4183,1824,4818,980,5473,1072,2890,673,2122,1431,651,2319,605,1901,2089,6463,1444,1815,542,833,1149,2540,1217,3562,826,2467,1408,3651,4138,850,3415,5862,3638,1171,1824,2137,974,1239,2472,2322,705,1111,2355,1314,2010,862,610,1173,1518,3924,799,1261,711,300,4472,457,436,2441,655,424],"type":"cmap","mtitle":"Total COVID-19 Tests","hovtext":"Total tests performed:","col1":"rgb(255, 255, 255)","col2":"rgb(232, 171, 255)","col3":"rgb(219, 122, 255)","col4":"rgb(160, 50, 201)","col5":"rgb(114, 2, 156)"},"active_cases":{"counties":["Shelby","Williamson","Davidson","Hamilton","Knox","Sullivan","Campbell","Jefferson","Rutherford","Anderson","Bradley","Sevier","Sumner","Tipton","Cheatham","Dekalb","McMinn","Maury","Wilson","Chester","Cumberland","Fayette","Hardin","Loudon","Marion","Montgomery","Putnam","Robertson","Blount","Carroll","Cocke","Dickson","Dyer","Franklin","Greene","Hamblen","Monroe","Roane","Scott","Washington","Humphreys","Gibson","Grundy","Henry","Hickman","Houston","Lawrence","Lewis","Lincoln","Macon","Madison","Marshall","Overton","Perry","Polk","Claiborne","Hawkins","McNairy","Morgan","Meigs","Wayne","Henderson","Bedford","Bledsoe","Cannon","Coffee","Hardeman","Trousdale","Unicoi","Weakley","White","Benton","Haywood","Warren","Carter","Decatur","Grainger","Johnson","Smith","Obion","Union","Clay","Fentress","Giles","Lauderdale","Jackson","Sequatchie","Crockett","Hancock","Lake","Moore","Pickett","Rhea","Stewart","Van Buren"],"z":[2099,304,2297,1026,181,2,3,15,1039,19,76,170,603,85,85,5,22,95,222,2,26,48,22,39,8,204,132,261,23,4,4,60,59,11,2,26,19,2,1,23,6,8,7,3,5,4,40,2,20,57,25,12,2,6,6,7,3,14,3,5,1,3,120,2,4,24,22,97,2,7,14,0,8,7,2,2,6,4,11,23,4,3,4,11,18,2,4,4,0,23,1,0,19,10,2],"type":"cmap","mtitle":"Active COVID-19 Cases","hovtext":"Active cases:","col1":"rgb(255, 255, 255)","col2":"rgb(158, 255, 182)","col3":"rgb(105, 255, 142)","col4":"rgb(50, 201, 88)","col5":"rgb(0, 138, 34)"},"daily_active":{"counties":["Shelby","Williamson","Davidson","Hamilton","Knox","Sullivan","Campbell","Jefferson","Rutherford","Anderson","Bradley","Sevier","Sumner","Tipton","Cheatham","Dekalb","McMinn","Maury","Wilson","Chester","Cumberland","Fayette","Hardin","Loudon","Marion","Montgomery","Putnam","Robertson","Blount","Carroll","Cocke","Dickson","Dyer","Franklin","Greene","Hamblen","Monroe","Roane","Scott","Washington","Humphreys","Gibson","Grundy","Henry","Hickman","Houston","Lawrence","Lewis","Lincoln","Macon","Madison","Marshall","Overton","Perry","Polk","Claiborne","Hawkins","McNairy","Morgan","Meigs","Wayne","Henderson","Bedford","Bledsoe","Cannon","Coffee","Hardeman","Trousdale","Unicoi","Weakley","White","Benton","Haywood","Warren","Carter","Decatur","Grainger","Johnson","Smith","Obion","Union","Clay","Fentress","Giles","Lauderdale","Jackson","Sequatchie","Crockett","Hancock","Lake","Moore","Pickett","Rhea","Stewart","Van Buren"],"z":[-1,5,59,10,14,0,-1,3,16,2,-3,34,1,5,-1,0,1,15,8,0,1,2,1,6,-1,12,15,4,3,0,0,-1,5,0,1,-1,4,-1,1,6,0,0,0,0,-1,0,3,0,-1,6,-1,-1,0,-5,-1,1,0,1,1,0,0,0,-4,0,0,-3,0,4,0,0,1,0,0,1,0,1,-1,1,1,1,0,0,0,1,0,1,0,2,0,-245,0,0,-4,1,0],"type":"cmap","mtitle":"Daily Change of Active COVID-19 Cases: 06/18/2020","hovtext":"Net change of active cases:","col1":"rgb(255, 255, 255)","col2":"rgb(158, 255, 182)","col3":"rgb(105, 255, 142)","col4":"rgb(50, 201, 88)","col5":"rgb(0, 138, 34)"},"total_recoveries":{"counties":["Shelby","Williamson","Davidson","Hamilton","Knox","Sullivan","Campbell","Jefferson","Rutherford","Anderson","Bradley","Sevier","Sumner","Tipton","Cheatham","Dekalb","McMinn","Maury","Wilson","Chester","Cumberland","Fayette","Hardin","Loudon","Marion","Montgomery","Putnam","Robertson","Blount","Carroll","Cocke","Dickson","Dyer","Franklin","Greene","Hamblen","Monroe","Roane","Scott","Washington","Humphreys","Gibson","Grundy","Henry","Hickman","Houston","Lawrence","Lewis","Lincoln","Macon","Madison","Marshall","Overton","Perry","Polk","Claiborne","Hawkins","McNairy","Morgan","Meigs","Wayne","Henderson","Bedford","Bledsoe","Cannon","Coffee","Hardeman","Trousdale","Unicoi","Weakley","White","Benton","Haywood","Warren","Carter","Decatur","Grainger","Johnson","Smith","Obion","Union","Clay","Fentress","Giles","Lauderdale","Jackson","Sequatchie","Crockett","Hancock","Lake","Moore","Pickett","Rhea","Stewart","Van Buren"],"z":[5033,426,4863,908,408,67,22,36,817,48,227,169,478,452,76,36,134,101,329,12,109,139,19,181,39,147,492,400,92,31,23,80,63,51,52,61,74,30,14,76,11,61,29,32,57,6,34,3,28,156,161,32,36,22,26,9,32,21,18,25,63,16,280,611,30,73,204,1362,50,29,35,7,29,29,20,13,16,22,34,44,5,8,11,13,52,19,19,14,1,666,4,4,224,7,3],"type":"cmap","mtitle":"Total COVID-19 Recoveries","hovtext":"Recovered cases:","col1":"rgb(255, 255, 255)","col2":"rgb(250, 255, 156)","col3":"rgb(248, 255, 102)","col4":"rgb(233, 242, 44)","col5":"rgb(165, 173, 0)"},"daily_recoveries":{"counties":["Shelby","Williamson","Davidson","Hamilton","Knox","Sullivan","Campbell","Jefferson","Rutherford","Anderson","Bradley","Sevier","Sumner","Tipton","Cheatham","Dekalb","McMinn","Maury","Wilson","Chester","Cumberland","Fayette","Hardin","Loudon","Marion","Montgomery","Putnam","Robertson","Blount","Carroll","Cocke","Dickson","Dyer","Franklin","Greene","Hamblen","Monroe","Roane","Scott","Washington","Humphreys","Gibson","Grundy","Henry","Hickman","Houston","Lawrence","Lewis","Lincoln","Macon","Madison","Marshall","Overton","Perry","Polk","Claiborne","Hawkins","McNairy","Morgan","Meigs","Wayne","Henderson","Bedford","Bledsoe","Cannon","Coffee","Hardeman","Trousdale","Unicoi","Weakley","White","Benton","Haywood","Warren","Carter","Decatur","Grainger","Johnson","Smith","Obion","Union","Clay","Fentress","Giles","Lauderdale","Jackson","Sequatchie","Crockett","Hancock","Lake","Moore","Pickett","Rhea","Stewart","Van Buren"],"z":[104,7,110,64,7,0,2,0,20,1,5,11,9,2,3,0,0,5,13,0,0,1,1,1,1,3,3,8,0,0,0,1,1,0,0,0,0,1,0,0,0,1,0,0,1,0,1,0,1,1,1,2,0,5,1,0,0,1,0,1,0,0,5,0,0,3,0,-1,0,1,0,0,0,0,1,0,1,0,2,0,0,0,0,0,0,0,0,0,0,245,0,0,4,0,0],"type":"cmap","mtitle":"Daily COVID-19 Recoveries: 06/18/2020","hovtext":"New recoveries:","col1":"rgb(255, 255, 255)","col2":"rgb(250, 255, 156)","col3":"rgb(248, 255, 102)","col4":"rgb(233, 242, 44)","col5":"rgb(165, 173, 0)"},"total_hospitalized":{"counties":["Shelby","Williamson","Davidson","Hamilton","Knox","Sullivan","Campbell","Jefferson","Rutherford","Anderson","Bradley","Sevier","Sumner","Tipton","Cheatham","Dekalb","McMinn","Maury","Wilson","Chester","Cumberland","Fayette","Hardin","Loudon","Marion","Montgomery","Putnam","Robertson","Blount","Carroll","Cocke","Dickson","Dyer","Franklin","Greene","Hamblen","Monroe","Roane","Scott","Washington","Humphreys","Gibson","Grundy","Henry","Hickman","Houston","Lawrence","Lewis","Lincoln","Macon","Madison","Marshall","Overton","Perry","Polk","Claiborne","Hawkins","McNairy","Morgan","Meigs","Wayne","Henderson","Bedford","Bledsoe","Cannon","Coffee","Hardeman","Trousdale","Unicoi","Weakley","White","Benton","Haywood","Warren","Carter","Decatur","Grainger","Johnson","Smith","Obion","Union","Clay","Fentress","Giles","Lauderdale","Jackson","Sequatchie","Crockett","Hancock","Lake","Moore","Pickett","Rhea","Stewart","Van Buren"],"z":[634,48,442,93,45,6,2,1,104,6,24,14,207,25,11,0,21,12,43,1,12,18,7,8,13,30,15,47,6,6,1,14,8,8,8,10,11,3,0,6,1,5,10,5,2,4,5,0,3,13,22,6,2,1,1,1,6,2,1,4,2,1,16,5,4,5,10,15,0,1,4,2,8,0,2,1,4,1,2,9,0,0,1,4,9,1,2,2,0,3,0,0,3,2,1],"type":"cmap","mtitle":"Total COVID-19 Hospitalizations","hovtext":"Total hospitalizations:","col1":"rgb(255, 255, 255)","col2":"rgb(255, 204, 163)","col3":"rgb(255, 175, 110)","col4":"rgb(222, 134, 62)","col5":"rgb(191, 86, 0)"},"daily_hospitalized":{"counties":["Shelby","Williamson","Davidson","Hamilton","Knox","Sullivan","Campbell","Jefferson","Rutherford","Anderson","Bradley","Sevier","Sumner","Tipton","Cheatham","Dekalb","McMinn","Maury","Wilson","Chester","Cumberland","Fayette","Hardin","Loudon","Marion","Montgomery","Putnam","Robertson","Blount","Carroll","Cocke","Dickson","Dyer","Franklin","Greene","Hamblen","Monroe","Roane","Scott","Washington","Humphreys","Gibson","Grundy","Henry","Hickman","Houston","Lawrence","Lewis","Lincoln","Macon","Madison","Marshall","Overton","Perry","Polk","Claiborne","Hawkins","McNairy","Morgan","Meigs","Wayne","Henderson","Bedford","Bledsoe","Cannon","Coffee","Hardeman","Trousdale","Unicoi","Weakley","White","Benton","Haywood","Warren","Carter","Decatur","Grainger","Johnson","Smith","Obion","Union","Clay","Fentress","Giles","Lauderdale","Jackson","Sequatchie","Crockett","Hancock","Lake","Moore","Pickett","Rhea","Stewart","Van Buren"],"z":[10,0,6,5,0,0,0,0,1,0,0,1,2,0,0,0,0,0,0,0,0,2,0,0,0,0,0,0,0,0,0,0,0,0,0,0,0,0,0,0,0,0,0,0,0,0,0,0,0,0,0,0,0,0,0,0,0,0,0,0,0,0,1,0,0,0,0,1,0,0,0,0,0,0,0,0,0,0,0,0,0,0,0,0,0,0,0,0,0,0,0,0,0,0,0],"type":"cmap","mtitle":"Daily COVID-19 Hospitalizations: 06/18/2020","hovtext":"New hospitalizations:","col1":"rgb(255, 255, 255)","col2":"rgb(255, 204, 163)","col3":"rgb(255, 175, 110)","col4":"rgb(222, 134, 62)","col5":"rgb(191, 86, 0)"}}
